<?xml version="1.0" encoding="UTF-8"?>
<objects serializationModel="Studio.02.00.00">
	<object class="AudioFile" id="{1e8cf794-7f15-48cc-8882-0f1ac170acc5}">
		<property name="assetPath">
			<value>Explore theme.aif</value>
		</property>
		<property name="isStreaming">
			<value>true</value>
		</property>
		<property name="frequencyInKHz">
			<value>44.0999985</value>
		</property>
		<property name="channelCount">
			<value>2</value>
		</property>
		<property name="length">
			<value>70.736848072562353</value>
		</property>
		<relationship name="masterAssetFolder">
			<destination>{ded193ad-7efd-46e5-8d52-cbaeb0877b7b}</destination>
		</relationship>
	</object>
</objects>
